stabbb/__init__.py
stabbb/stab_bb.py
stabbb/tests/__init__.py
stabbb/tests/test_minimization.py
stabbb-0.0.0.1.dist-info/LICENSE
stabbb-0.0.0.1.dist-info/METADATA
stabbb-0.0.0.1.dist-info/WHEEL
stabbb-0.0.0.1.dist-info/top_level.txt
stabbb-0.0.0.1.dist-info/RECORD
