Metadata-Version: 2.1
Name: stabbb
Version: 0.0.0.1
Summary: Implementation of stabilized Barzilai-Borwein Method for gradient descent problems
Home-page: https://github.com/mesquita-daniel/StabBB
Author: Daniel Mesquita
License: UNKNOWN
Keywords: Optimization,Gardient Descent,Line Search
Platform: UNKNOWN
Classifier: Environment :: Console
Classifier: Operating System :: OS Independent
Classifier: Intended Audience :: Science/Research
Classifier: Programming Language :: Python
Classifier: Programming Language :: Python :: 3
Classifier: Programming Language :: Python :: 3.6
Classifier: Programming Language :: Python :: 3.7
Classifier: Programming Language :: Python :: 3.8
Classifier: Programming Language :: Cython
Classifier: Topic :: Scientific/Engineering :: Mathematics
